{
	"names": [
		{
			"region": "default",
			"roman": "Falke"
		},
		{
			"region": "japan",
			"roman": "Falke",
			"original": "ファルケ"
                }
	],
	"images": {
		"face": "falke.webp"
	},
	"moves": {
		"{normalThrows}": [
			{
				"name": "Wirbel Wind",
				"input": "[LP]+[LK]"
			},
			{
				"name": "Luftstrom",
				"input": ":b:+[LP]+[LK]"
			},
			{
				"name": "Windstoss",
				"input": "{inAirAndClose} [LP]+[LK]"
			}	
		],
		"{v-trigger1}": [
			{
				"name": "Staerken",
				"input": "[HP]+[HK]"
			}	
		],
		"{v-trigger2}": [
			{
				"name": "Psycho Angriff",
				"input": "[HP]+[HK]"
			}
		],
		"{v-skill}": [
			{
				"name": "Psycho Trombe",
				"input": "[MP]+[MK]"
			}
		],
		"{v-reversal}": [
			{
				"name": "Psycho Impulse",
				"input": ":f:+[LP]+[MP]+[HP]",
				"extraInfo": "{whileBlocking}"
			}		
		],
		"{uniqueAttacks}": [
			{
				"name": "Psycho Spitze",
				"input": ":f:+[HP]"
			},
			{
				"name": "Blaukraehe",
				"input": ":df:+[HK]"
			},
			{
				"name": "Luftjagd",
				"input": "{inAir} :d:+[MK]"
			}
		],
		"{specialMoves}": [
			{
				"name": "Psycho Kugel",
				"input": "{hold} [HP] {then} {release} {whileStanding}",
				"canBeUpgraded": false
			},
			{
				"name": "Psycho Kanonen",
				"input": "{hold} [HP] {then} {release} {whileCrouching}",
				"canBeUpgraded": false
			},
			{
				"name": "Psycho Feder",
				"input": "{hold} [HP] {then} {release} {inAir}",
				"canBeUpgraded": false
			},
			{
				"name": "Psycho Schneide",
				"input": "[P]+[P]",
				"canBeUpgraded": true, "costOfUpgrade": 1,
				"extraInfo": "{psychoSchneideEX}"
			},
			{
				"name": "Katapult",
				"input": "[K]+[K]",
				"canBeUpgraded": true, "costOfUpgrade": 1,
				"extraInfo": "{katapultEX}"
			},
			{
				"name": "Psycho Schrot",
				"input": "[HP]+[HK]",
				"extraInfo": "{duringVTrigger1}"
			},
			{
				"name": "Psycho Panzer",
				"input": ":d:+[HP]+[HK]",
				"extraInfo": "{duringVTrigger1}"
			},
			{
				"name": "Psycho Jaeger",
				"input": "{inAir} [HP]+[HK]",
				"extraInfo": "{duringVTrigger1}"
			},
			{
				"name": "Psycho Sturm",
				"input": "[HP]+[HK]",
				"extraInfo": "{duringVTrigger2}"
			},
			{
				"name": "Psycho Klinge",
				"input": ":d:+[HP]+[HK]",
				"extraInfo": "{duringVTrigger2}"
			}
		],
		"{critical-art}": [
			{
				"name": "Psycho Fluegel",
				"input": ":qcf::qcf:+[P]"
			}
		]
	},
	"custom_strings": {
		"english": [
			{ "or": "or"},
			{ "airOK":"can be done in the air"},
			{ "close": "close"},
			{ "inAir" : "in the air" },
			{ "duringJumpNearWall" : "during jump near wall"},
			{ "inAirAndClose" : "close to the opponent in the air"},
			{ "whileBlocking": "while blocking"},
			{ "tapPunch": "tap [P] repeatedly"},
			{ "tapKick": "tap [K] repeatedly"},
			{ "holdToAttack" : "hold buttons to attack"},
			{ "holdToExtend" : "hold buttons to extend"},
			{ "holdToCharge" : "hold buttons to charge"},
			{ "holdHKToAttack": "hold HK to attack"},
			{ "press": "press"},
			{ "hold": "hold"},
			{ "toDelay": "to delay"},
			{ "toCharge": "to charge"},
			{ "toExtend": "to extend the duration"},
			{ "charge": "charge"},
			{ "duringVTrigger1": "during V-Trigger 1"},
			{ "duringVTrigger2": "during V-Trigger 2"},
			{ "duringForwardJump": "during forward jump" },
			{ "duringVerticalJump": "during vertical jump"},
			{ "duringVerticalOrForwardJump":"during vertical or forward jump"},
			{ "duringDash" : "during a dash"},
			{ "doNothing": "do nothing"},
			{ "onCrouchingOpponent": "on a crouching opponent"},
			{ "useBOrFToMove": "use :b: or :f: to move"},
			//FALKE SF5 SPECIFIC
			{ "whileStanding": "while standing" },
			{ "whileCrouching": "while crouching" },
			{ "psychoSchneideEX": "EX version done with [LP]+[MP]+[HP]"},
			{ "katapultEX": "EX version done with [LK]+[MK]+[HK]"}

		],
		"portuguese": [
			{ "or": "ou"},
			{ "airOK":"também pode ser feito no ar"},
			{ "close": "perto"},
			{ "inAir" : "no ar" },
			{ "duringJumpNearWall" : "durante um pulo, próximo à parede"},
			{ "inAirAndClose" : "perto do oponente, no ar"},
			{ "whileBlocking": "ao defender"},
			{ "tapPunchForMoreHits": "aperte [P] repetidamente para mais hits"},
			{ "tapPunch": "aperte [P] repetidamente"},
			{ "tapKick": "aperte [K] repetidamente"},
			{ "holdToAttack" : "segure os botões para atacar"},
			{ "holdToExtend" : "segure os botões aumentar a duração"},
			{ "holdToCharge" : "segure os botões para aumentar a força do golpe"},
			{ "holdHKToAttack": "segure HK para atacar"},
			{ "press": "aperte"},
			{ "hold": "segure"},
			{ "toDelay": "para atrasar"},
			{ "toCharge": "para aumentar a força do golpe"},
			{ "toExtend": "para aumentar a duração"},
			{ "charge": "segure"},
			{ "duringVTrigger1": "durante o V-Trigger 1"},
			{ "duringVTrigger2": "durante o V-Trigger 2"},
			{ "duringForwardJump": "durante um pulo para frente" },
			{ "duringVerticalJump": "durante um pulo reto"},
			{ "duringVerticalOrForwardJump":"durante um pulo reto ou um pulo para frente"},
			{ "duringDash" : "durante um dash"},
			{ "doNothing": "não faça nada"},
			{ "onCrouchingOpponent": "em um oponente abaixado"},
			{ "useBOrFToMove": "use :b: ou :f: para se mover"},
			//FALKE SF5 SPECIFIC
			{ "whileStanding": "em pé" },
			{ "whileCrouching": "ao abaixar" },
			{ "psychoSchneideEX": "versão EX é feita com [LP]+[MP]+[HP]"},
			{ "katapultEX": "versão EX é feita com [LK]+[MK]+[HK]"}
		]
	}
}